note_seq/__init__.py
note_seq/abc_parser.py
note_seq/abc_parser_test.py
note_seq/audio_io.py
note_seq/audio_io_test.py
note_seq/chord_inference.py
note_seq/chord_inference_test.py
note_seq/chord_symbols_lib.py
note_seq/chord_symbols_lib_test.py
note_seq/chords_encoder_decoder.py
note_seq/chords_encoder_decoder_test.py
note_seq/chords_lib.py
note_seq/chords_lib_test.py
note_seq/constants.py
note_seq/drums_encoder_decoder.py
note_seq/drums_encoder_decoder_test.py
note_seq/drums_lib.py
note_seq/drums_lib_test.py
note_seq/encoder_decoder.py
note_seq/encoder_decoder_test.py
note_seq/events_lib.py
note_seq/events_lib_test.py
note_seq/lead_sheets_lib.py
note_seq/lead_sheets_lib_test.py
note_seq/melodies_lib.py
note_seq/melodies_lib_test.py
note_seq/melody_encoder_decoder.py
note_seq/melody_encoder_decoder_test.py
note_seq/melody_inference.py
note_seq/melody_inference_test.py
note_seq/midi_io.py
note_seq/midi_io_test.py
note_seq/midi_synth.py
note_seq/musicnet_io.py
note_seq/musicnet_io_test.py
note_seq/musicxml_parser.py
note_seq/musicxml_parser_test.py
note_seq/musicxml_reader.py
note_seq/notebook_utils.py
note_seq/performance_controls.py
note_seq/performance_controls_test.py
note_seq/performance_encoder_decoder.py
note_seq/performance_encoder_decoder_test.py
note_seq/performance_lib.py
note_seq/performance_lib_test.py
note_seq/pianoroll_encoder_decoder.py
note_seq/pianoroll_encoder_decoder_test.py
note_seq/pianoroll_lib.py
note_seq/pianoroll_lib_test.py
note_seq/sequences_lib.py
note_seq/sequences_lib_test.py
note_seq/testing_lib.py
note_seq/version.py
note_seq/protobuf/__init__.py
note_seq/protobuf/compare.py
note_seq/protobuf/generator_pb2.py
note_seq/protobuf/generator_pb2.pyi
note_seq/protobuf/music_pb2.py
note_seq/protobuf/music_pb2.pyi
note_seq-0.0.5.dist-info/LICENSE
note_seq-0.0.5.dist-info/METADATA
note_seq-0.0.5.dist-info/WHEEL
note_seq-0.0.5.dist-info/top_level.txt
note_seq-0.0.5.dist-info/RECORD
